seeder/__init__.py
seeder/base.py
seeder/builders.py
seeder/cli.py
seeder/generators.py
seeder/logging.py
seeder/ordering.py
seeder/registry.py
djseed-0.1.4.dist-info/LICENSE
djseed-0.1.4.dist-info/METADATA
djseed-0.1.4.dist-info/WHEEL
djseed-0.1.4.dist-info/entry_points.txt
djseed-0.1.4.dist-info/RECORD
