Metadata-Version: 2.3
Name: djseed
Version: 0.1.4
Summary: Utility to generate synthetic fixture data for Django projects.
License: MIT License
Keywords: django,fixtures,seeding,faker,testing
Author: Almerindo Uazela
Author-email: almerindo.uazela@gmail.com
Requires-Python: >=3.10
Classifier: Development Status :: 3 - Alpha
Classifier: Environment :: Web Environment
Classifier: Framework :: Django
Classifier: Intended Audience :: Developers
Classifier: License :: OSI Approved :: MIT License
Classifier: Programming Language :: Python
Classifier: Programming Language :: Python :: 3
Classifier: Programming Language :: Python :: 3.10
Classifier: Programming Language :: Python :: 3.11
Classifier: Programming Language :: Python :: 3.12
Classifier: Programming Language :: Python :: 3.13
Classifier: Topic :: Database
Classifier: Topic :: Software Development :: Testing
Requires-Dist: django (>=5.2.1,<6.0.0)
Requires-Dist: faker (>=37.3.0,<38.0.0)
